[
  {
    "username": "Administrator!",
    "text": "Hehe",
    "time": "13:08"
  },
  {
    "username": "SOme",
    "text": "yo",
    "time": "13:11"
  },
  {
    "username": "Arabasko",
    "text": "Yey",
    "time": "13:11"
  },
  {
    "username": "azazalkapro",
    "text": "Hey There",
    "time": "09:32"
  },
  {
    "username": "Huesos",
    "text": "privet",
    "time": "11:22"
  },
  {
    "username": "Huesos",
    "text": "d",
    "time": "12:55"
  },
  {
    "username": "Huesos",
    "text": "Eyo",
    "time": "16:23"
  },
  {
    "username": "Huesos",
    "text": "e",
    "time": "16:27"
  }
]